AUTHORS
CHANGES
LICENSE
MANIFEST.in
Makefile
README.rst
setup.cfg
setup.py
docs/Makefile
docs/conf.py
docs/index.rst
docs/make.bat
docs/api/index.rst
docs/api/pybankreader.formats.bbf.rst
docs/api/pybankreader.formats.gpc.rst
docs/api/pybankreader.formats.rst
docs/formats/index.rst
docs/tutorial/fields.rst
docs/tutorial/general.rst
docs/tutorial/index.rst
docs/tutorial/records.rst
docs/tutorial/reports.rst
pybankreader/__init__.py
pybankreader/exceptions.py
pybankreader/fields.py
pybankreader/records.py
pybankreader/reports.py
pybankreader/utils.py
pybankreader.egg-info/PKG-INFO
pybankreader.egg-info/SOURCES.txt
pybankreader.egg-info/dependency_links.txt
pybankreader.egg-info/pbr.json
pybankreader.egg-info/requires.txt
pybankreader.egg-info/top_level.txt
pybankreader.egg-info/zip-safe
pybankreader/formats/__init__.py
pybankreader/formats/bbf/__init__.py
pybankreader/formats/bbf/records.py
pybankreader/formats/bbf/reports.py
pybankreader/formats/gpc/__init__.py
pybankreader/formats/gpc/records.py
pybankreader/formats/gpc/reports.py
tests/conftest.py
tests/test_bbf_records.py
tests/test_bbf_reports.py
tests/test_exceptions.py
tests/test_fields.py
tests/test_gpc_records.py
tests/test_gpc_reports.py
tests/test_records.py
tests/test_reports.py