Metadata-Version: 1.1
Name: pybankreader
Version: 0.2.3
Summary: A library & micro-framework for reading data files exported from various internet banking solutions. Currently supports BBF and GPC files (just subsets of those for the time being)
Home-page: http://github.com/baldman/pybankreader
Author: Tomáš Plešek
Author-email: tomas@plesek.cz
License: BSD
Platform: any
Classifier: Development Status :: 5 - Production/Stable
Classifier: Environment :: Plugins
Classifier: Intended Audience :: Developers
Classifier: License :: OSI Approved :: BSD License
Classifier: Operating System :: OS Independent
Classifier: Programming Language :: Python
Classifier: Programming Language :: Python :: 2.7
Classifier: Programming Language :: Python :: 3.4
Classifier: Topic :: Software Development :: Libraries :: Python Modules
